uFire_Mod_ORP/__init__.py
uFire_Mod_ORP/shell.py
uFire_Mod_ORP/uFire_Mod_ORP.py
uFire_Mod_ORP-0.9.0.dist-info/LICENSE
uFire_Mod_ORP-0.9.0.dist-info/METADATA
uFire_Mod_ORP-0.9.0.dist-info/WHEEL
uFire_Mod_ORP-0.9.0.dist-info/top_level.txt
uFire_Mod_ORP-0.9.0.dist-info/RECORD
