Metadata-Version: 2.1
Name: uFire-Mod-ORP
Version: 0.9.0
Summary: Add the ability to measure ORP to your hardware application with a fully digital interface.
Home-page: https://ufire.dev
Author: Microfire LLC
Author-email: contact@ufire.co
License: UNKNOWN
Project-URL: Bug Tracker, https://github.com/u-fire/Mod-ORP/issues
Platform: UNKNOWN
Classifier: Programming Language :: Python :: 3
Classifier: License :: OSI Approved :: MIT License
Classifier: Operating System :: OS Independent
Requires-Python: >=3.6
